pymad8/Input.py
pymad8/Output.py
pymad8/Plot.py
pymad8/Sim.py
pymad8/Track.py
pymad8/Visualisation.py
pymad8/__init__.py
pymad8/_version.py
pymad8-2.0.2.dist-info/COPYING.txt
pymad8-2.0.2.dist-info/LICENSE.txt
pymad8-2.0.2.dist-info/METADATA
pymad8-2.0.2.dist-info/WHEEL
pymad8-2.0.2.dist-info/top_level.txt
pymad8-2.0.2.dist-info/RECORD
